[
    {
        "title": "SRS",
        "content": ""
    },
    {
        "title": "WBS",
        "content": ""
    },
    {
        "title": "CLASS DIAGRAM",
        "content": ""
    },
    {
        "title": "USE CASE DIAGRAM",
        "content": ""
    },
    {
        "title": "ACTIVITY DIAGRAM",
        "content": ""
    },
    {
        "title": "DATA FLOW DIAGRAM",
        "content": ""
    },
    {
        "title": "STATE CHART DIAGRAM",
        "content": ""
    },
    {
        "title": "ER DIAGRAM",
        "content": ""
    }
]